softgraph/__init__.py
softgraph/onecall.py
softgraph/datasets/features.py
softgraph/datasets/sbm.py
softgraph/datasets/signed.py
softgraph/datasets/temporal.py
softgraph/deep/node.py
softgraph/train/edge.py
softgraph/train/node.py
softgraph/train/temporal.py
softgraph/utils/metrics.py
softgraph/utils/viz.py
softgraph-0.3.0.dist-info/METADATA
softgraph-0.3.0.dist-info/WHEEL
softgraph-0.3.0.dist-info/RECORD
