Metadata-Version: 2.4
Name: softgraph
Version: 0.3.0
Summary: Graph ML in one call: node/edge/temporal + MLP/GCN/SAGE (optional) + useful plots.
Project-URL: Homepage, https://github.com/soft-tech-talks/softgraph
Author-email: Soft Tech Talks <hello@softtechtalks.org>
License: MIT
Requires-Python: >=3.9
Requires-Dist: matplotlib>=3.7
Requires-Dist: networkx>=3.2
Requires-Dist: numpy>=1.24
Requires-Dist: pandas>=2.1
Requires-Dist: scikit-learn>=1.3
Requires-Dist: scipy>=1.10
Provides-Extra: deep
Requires-Dist: torch>=2.1; extra == 'deep'
